tmurkser/__init__.py
tmurkser/config_file.py
tmurkser/dataclasses.py
tmurkser/main.py
tmurkser/session_loader.py
tmurkser/session_saver.py
tmurkser-0.1.0.dist-info/METADATA
tmurkser-0.1.0.dist-info/WHEEL
tmurkser-0.1.0.dist-info/entry_points.txt
tmurkser-0.1.0.dist-info/licenses/LICENSE
tmurkser-0.1.0.dist-info/RECORD
