Metadata-Version: 2.4
Name: tmurkser
Version: 0.1.0
Summary: Simple tmux session manager
Project-URL: Homepage, https://github.com/Data5tream/tmurkser
Project-URL: Issues, https://github.com/Data5tream/tmurkser/issues
Author-email: Simon Barth <data5tream@protonmail.com>
License-Expression: MIT
License-File: LICENSE
Requires-Python: <4.0,>=3.12
Requires-Dist: libtmux>=0.46.1
Requires-Dist: tomlkit>=0.13.2
